vik/.vimrc
vik/__init__.py
vik/vik.py
vik-1.0.4.dist-info/LICENSE
vik-1.0.4.dist-info/METADATA
vik-1.0.4.dist-info/WHEEL
vik-1.0.4.dist-info/entry_points.txt
vik-1.0.4.dist-info/top_level.txt
vik-1.0.4.dist-info/RECORD
