Metadata-Version: 2.1
Name: vik
Version: 1.0.4
Summary: KEK extension for Vim
Author: SweetBubaleXXX
License: GNU General Public License v3.0
Project-URL: Source, https://github.com/SweetBubaleXXX/vik
Requires-Python: >=3.10
License-File: LICENSE
Requires-Dist: gnukek-cli
